chatrouter.py
chatrouter-1.0.3.dist-info/LICENSE
chatrouter-1.0.3.dist-info/METADATA
chatrouter-1.0.3.dist-info/WHEEL
chatrouter-1.0.3.dist-info/RECORD
