Metadata-Version: 2.1
Name: chatrouter
Version: 1.0.3
Summary: router for chatbot
License: MIT
Author: guangrei
Requires-Python: >=3.10,<4.0
Classifier: License :: OSI Approved :: MIT License
Classifier: Programming Language :: Python :: 3
Classifier: Programming Language :: Python :: 3.10
Classifier: Programming Language :: Python :: 3.11
Classifier: Programming Language :: Python :: 3.12
